Workbook

Sheet Gantt
A1: ID | B1: Phase | C1: Task | D1: Model | E1: Start | F1: End | G1: Work days | H1: Depends on | I1: % Complete | J1: Status | K1: Done days | L1: 46286 | M1: 46293 | N1: 46300 | O1: 46307 | P1: 46314 | Q1: 46321 | R1: 46328 | S1: 46335 | T1: 46342 | U1: 46349 | V1: 46356 | W1: 46363 | X1: 46370 | Y1: 46377 | Z1: 46384 | AA1: 46391 | AB1: 46398 | AC1: 46405 | AD1: 46412 | AE1: 46419 | AF1: 46426
A2: T0.1 | B2: P0 | C2: Overview & design brief | D2: human | E2: 46286 | F2: 46288 | G2: 3 | I2: 1 | J2: =IF(I2>=1,"Done",IF(TODAY()>F2,"Late",IF(I2>0,"In progress","Not started"))) | K2: =G2*I2
A3: T0.2 | B3: P0 | C3: Detailed specs + adversarial review | D3: human | E3: 46289 | F3: 46290 | G3: 3 | H3: T0.1 | I3: 1 | J3: =IF(I3>=1,"Done",IF(TODAY()>F3,"Late",IF(I3>0,"In progress","Not started"))) | K3: =G3*I3
A4: T0.3 | B4: P0 | C4: Gantt, review deck, OKRs | D4: human | E4: 46291 | F4: 46291 | G4: 1 | H4: T0.2 | I4: 1 | J4: =IF(I4>=1,"Done",IF(TODAY()>F4,"Late",IF(I4>0,"In progress","Not started"))) | K4: =G4*I4
A5: T0.4 | B5: P0 | C5: Owner review & sign-off of plan | D5: human | E5: 46293 | F5: 46295 | G5: 3 | H5: T0.3 | I5: 1 | J5: =IF(I5>=1,"Done",IF(TODAY()>F5,"Late",IF(I5>0,"In progress","Not started"))) | K5: =G5*I5
A6: T1.1 | B6: P1 | C6: Repo scaffold: cargo workspace, icp.yaml, toolch… | D6: haiku-4.5 | E6: 46296 | F6: 46296 | G6: 1 | H6: T0.4 | I6: 1 | J6: =IF(I6>=1,"Done",IF(TODAY()>F6,"Late",IF(I6>0,"In progress","Not started"))) | K6: =G6*I6
A7: T1.2 | B7: P1 | C7: sc-types shared crate (types, ApiError, limits) | D7: sonnet-5 | E7: 46297 | F7: 46300 | G7: 2 | H7: T1.1 | I7: 1 | J7: =IF(I7>=1,"Done",IF(TODAY()>F7,"Late",IF(I7>0,"In progress","Not started"))) | K7: =G7*I7
A8: T1.3 | B8: P1 | C8: Local verification & deploy harness (verify-loca… | D8: haiku-4.5 | E8: 46297 | F8: 46300 | G8: 2 | H8: T1.1 | I8: 1 | J8: =IF(I8>=1,"Done",IF(TODAY()>F8,"Late",IF(I8>0,"In progress","Not started"))) | K8: =G8*I8
A9: T1.4 | B9: P1 | C9: PocketIC harness with ICP ledger + CMC wasms | D9: sonnet-5 | E9: 46297 | F9: 46300 | G9: 2 | H9: T1.1 | I9: 1 | J9: =IF(I9>=1,"Done",IF(TODAY()>F9,"Late",IF(I9>0,"In progress","Not started"))) | K9: =G9*I9
A10: SP-7 | B10: P1 | C10: Spike: Galaxy Zoo JWST (CEERS) labels, licence, … | D10: sonnet-5 | E10: 46301 | F10: 46301 | G10: 1 | H10: T0.4 | I10: 1 | J10: =IF(I10>=1,"Done",IF(TODAY()>F10,"Late",IF(I10>0,"In progress","Not started"))) | K10: =G10*I10
A11: T1.5 | B11: P1 | C11: JWST subject selection + gold (DJA v7 catalogs, … | D11: sonnet-5 | E11: 46302 | F11: 46308 | G11: 5 | H11: SP-7 | I11: 0 | J11: =IF(I11>=1,"Done",IF(TODAY()>F11,"Late",IF(I11>0,"In progress","Not started"))) | K11: =G11*I11
A12: T1.7 | B12: P1 | C12: Render dossiers (cutouts, RGB, dossier.json) + R… | D12: sonnet-5 | E12: 46309 | F12: 46315 | G12: 5 | H12: T1.5 | I12: 0 | J12: =IF(I12>=1,"Done",IF(TODAY()>F12,"Late",IF(I12>0,"In progress","Not started"))) | K12: =G12*I12
A13: SP-1 | B13: P1 | C13: Spike: CMC + ICRC-2 memo behaviour | D13: sonnet-5 | E13: 46301 | F13: 46301 | G13: 1 | H13: T1.4 | I13: 1 | J13: =IF(I13>=1,"Done",IF(TODAY()>F13,"Late",IF(I13>0,"In progress","Not started"))) | K13: =G13*I13
A14: SP-3 | B14: P1 | C14: Spike: frozen canister query behaviour | D14: haiku-4.5 | E14: 46301 | F14: 46301 | G14: 1 | H14: T1.4 | I14: 1 | J14: =IF(I14>=1,"Done",IF(TODAY()>F14,"Late",IF(I14>0,"In progress","Not started"))) | K14: =G14*I14
... A100: T8.9 | B100: P8 | C100: Enable BTC/ETH on production (card stays off) | D100: human | E100: 46428 | F100: 46428 | G100: 1 | H100: T8.6,T8.8 | I100: 0 | J100: =IF(I100>=1,"Done",IF(TODAY()>F100,"Late",IF(I100>0,"In progress","Not started"))) | K100: =G100*I100

Sheet Progress
A1: Phase | B1: Tasks | C1: Work days | D1: Done | E1: In progress | F1: Late | G1: % complete (effort-weighted) | H1: Start | I1: End | J1: Name
A2: P0 | B2: =COUNTIF(Gantt!$B:$B,A2) | C2: =SUMIF(Gantt!$B:$B,A2,Gantt!$G:$G) | D2: =COUNTIFS(Gantt!$B:$B,A2,Gantt!$J:$J,"Done") | E2: =COUNTIFS(Gantt!$B:$B,A2,Gantt!$J:$J,"In progress") | F2: =COUNTIFS(Gantt!$B:$B,A2,Gantt!$J:$J,"Late*") | G2: =IF(C2>0,SUMIF(Gantt!$B:$B,A2,Gantt!$K:$K)/C2,0) | H2: 46286 | I2: 46295 | J2: Planning
A3: P1 | B3: =COUNTIF(Gantt!$B:$B,A3) | C3: =SUMIF(Gantt!$B:$B,A3,Gantt!$G:$G) | D3: =COUNTIFS(Gantt!$B:$B,A3,Gantt!$J:$J,"Done") | E3: =COUNTIFS(Gantt!$B:$B,A3,Gantt!$J:$J,"In progress") | F3: =COUNTIFS(Gantt!$B:$B,A3,Gantt!$J:$J,"Late*") | G3: =IF(C3>0,SUMIF(Gantt!$B:$B,A3,Gantt!$K:$K)/C3,0) | H3: 46296 | I3: 46315 | J3: Foundations & spikes
A4: P2 | B4: =COUNTIF(Gantt!$B:$B,A4) | C4: =SUMIF(Gantt!$B:$B,A4,Gantt!$G:$G) | D4: =COUNTIFS(Gantt!$B:$B,A4,Gantt!$J:$J,"Done") | E4: =COUNTIFS(Gantt!$B:$B,A4,Gantt!$J:$J,"In progress") | F4: =COUNTIFS(Gantt!$B:$B,A4,Gantt!$J:$J,"Late*") | G4: =IF(C4>0,SUMIF(Gantt!$B:$B,A4,Gantt!$K:$K)/C4,0) | H4: 46304 | I4: 46321 | J4: Platform core
A5: P3 | B5: =COUNTIF(Gantt!$B:$B,A5) | C5: =SUMIF(Gantt!$B:$B,A5,Gantt!$G:$G) | D5: =COUNTIFS(Gantt!$B:$B,A5,Gantt!$J:$J,"Done") | E5: =COUNTIFS(Gantt!$B:$B,A5,Gantt!$J:$J,"In progress") | F5: =COUNTIFS(Gantt!$B:$B,A5,Gantt!$J:$J,"Late*") | G5: =IF(C5>0,SUMIF(Gantt!$B:$B,A5,Gantt!$K:$K)/C5,0) | H5: 46318 | I5: 46332 | J5: AAA canister & agent kit
A6: P4 | B6: =COUNTIF(Gantt!$B:$B,A6) | C6: =SUMIF(Gantt!$B:$B,A6,Gantt!$G:$G) | D6: =COUNTIFS(Gantt!$B:$B,A6,Gantt!$J:$J,"Done") | E6: =COUNTIFS(Gantt!$B:$B,A6,Gantt!$J:$J,"In progress") | F6: =COUNTIFS(Gantt!$B:$B,A6,Gantt!$J:$J,"Late*") | G6: =IF(C6>0,SUMIF(Gantt!$B:$B,A6,Gantt!$K:$K)/C6,0) | H6: 46328 | I6: 46357 | J6: Review, consensus & credits
A7: P5 | B7: =COUNTIF(Gantt!$B:$B,A7) | C7: =SUMIF(Gantt!$B:$B,A7,Gantt!$G:$G) | D7: =COUNTIFS(Gantt!$B:$B,A7,Gantt!$J:$J,"Done") | E7: =COUNTIFS(Gantt!$B:$B,A7,Gantt!$J:$J,"In progress") | F7: =COUNTIFS(Gantt!$B:$B,A7,Gantt!$J:$J,"Late*") | G7: =IF(C7>0,SUMIF(Gantt!$B:$B,A7,Gantt!$K:$K)/C7,0) | H7: 46336 | I7: 46372 | J7: Payments
A8: P6 | B8: =COUNTIF(Gantt!$B:$B,A8) | C8: =SUMIF(Gantt!$B:$B,A8,Gantt!$G:$G) | D8: =COUNTIFS(Gantt!$B:$B,A8,Gantt!$J:$J,"Done") | E8: =COUNTIFS(Gantt!$B:$B,A8,Gantt!$J:$J,"In progress") | F8: =COUNTIFS(Gantt!$B:$B,A8,Gantt!$J:$J,"Late*") | G8: =IF(C8>0,SUMIF(Gantt!$B:$B,A8,Gantt!$K:$K)/C8,0) | H8: 46372 | I8: 46407 | J8: Frontend
A9: P7 | B9: =COUNTIF(Gantt!$B:$B,A9) | C9: =SUMIF(Gantt!$B:$B,A9,Gantt!$G:$G) | D9: =COUNTIFS(Gantt!$B:$B,A9,Gantt!$J:$J,"Done") | E9: =COUNTIFS(Gantt!$B:$B,A9,Gantt!$J:$J,"In progress") | F9: =COUNTIFS(Gantt!$B:$B,A9,Gantt!$J:$J,"Late*") | G9: =IF(C9>0,SUMIF(Gantt!$B:$B,A9,Gantt!$K:$K)/C9,0) | H9: 46373 | I9: 46408 | J9: Hardening
A10: P8 | B10: =COUNTIF(Gantt!$B:$B,A10) | C10: =SUMIF(Gantt!$B:$B,A10,Gantt!$G:$G) | D10: =COUNTIFS(Gantt!$B:$B,A10,Gantt!$J:$J,"Done") | E10: =COUNTIFS(Gantt!$B:$B,A10,Gantt!$J:$J,"In progress") | F10: =COUNTIFS(Gantt!$B:$B,A10,Gantt!$J:$J,"Late*") | G10: =IF(C10>0,SUMIF(Gantt!$B:$B,A10,Gantt!$K:$K)/C10,0) | H10: 46296 | I10: 46429 | J10: Beta & launch
A11: P9 | B11: =COUNTIF(Gantt!$B:$B,A11) | C11: =SUMIF(Gantt!$B:$B,A11,Gantt!$G:$G) | D11: =COUNTIFS(Gantt!$B:$B,A11,Gantt!$J:$J,"Done") | E11: =COUNTIFS(Gantt!$B:$B,A11,Gantt!$J:$J,"In progress") | F11: =COUNTIFS(Gantt!$B:$B,A11,Gantt!$J:$J,"Late*") | G11: =IF(C11>0,SUMIF(Gantt!$B:$B,A11,Gantt!$K:$K)/C11,0) | H11: 46409 | I11: 46426 | J11: Design & polish (after function)
A12: Overall | B12: =SUM(B2:B11) | C12: =SUM(C2:C11) | D12: =SUM(D2:D11) | E12: =SUM(E2:E11) | F12: =SUM(F2:F11) | G12: =IF(C12>0,SUM(Gantt!K2:K100)/C12,0) | H12: 46286 | I12: 46429
A14: Edit only % Complete on the Gantt tab; everything else updates. Detail: docs/specs/10-tasks.md

Sheet Milestones
A1: Milestone | B1: Gate task | C1: Target date | D1: Status
A2: M1 Foundations + JWST data ready | B2: T1.7 | C2: =INDEX(Gantt!$F:$F,MATCH(B2,Gantt!$A:$A,0)) | D2: =INDEX(Gantt!$J:$J,MATCH(B2,Gantt!$A:$A,0))
A3: M2 Local alpha: agent classifies end-to-end | B3: T3.8 | C3: =INDEX(Gantt!$F:$F,MATCH(B3,Gantt!$A:$A,0)) | D3: =INDEX(Gantt!$J:$J,MATCH(B3,Gantt!$A:$A,0))
A4: M3 Review & credits complete | B4: T4.8 | C4: =INDEX(Gantt!$F:$F,MATCH(B4,Gantt!$A:$A,0)) | D4: =INDEX(Gantt!$J:$J,MATCH(B4,Gantt!$A:$A,0))
A5: M4 Payments complete | B5: T5.7 | C5: =INDEX(Gantt!$F:$F,MATCH(B5,Gantt!$A:$A,0)) | D5: =INDEX(Gantt!$J:$J,MATCH(B5,Gantt!$A:$A,0))
A6: M5 Frontend feature-complete (unstyled) | B6: T6.10 | C6: =INDEX(Gantt!$F:$F,MATCH(B6,Gantt!$A:$A,0)) | D6: =INDEX(Gantt!$J:$J,MATCH(B6,Gantt!$A:$A,0))
A7: M5b Design applied | B7: T9.5 | C7: =INDEX(Gantt!$F:$F,MATCH(B7,Gantt!$A:$A,0)) | D7: =INDEX(Gantt!$J:$J,MATCH(B7,Gantt!$A:$A,0))
A8: M6 Staging loaded & beta-ready backend | B8: T8.2 | C8: =INDEX(Gantt!$F:$F,MATCH(B8,Gantt!$A:$A,0)) | D8: =INDEX(Gantt!$J:$J,MATCH(B8,Gantt!$A:$A,0))
A9: M7 Public launch | B9: T8.7 | C9: =INDEX(Gantt!$F:$F,MATCH(B9,Gantt!$A:$A,0)) | D9: =INDEX(Gantt!$J:$J,MATCH(B9,Gantt!$A:$A,0))
